COPYING
MANIFEST.in
README.md
RELEASE-VERSION
SConstruct
pavement.py
paver-minilib.zip
setup.py
version.py
teensy_minimal_rpc/ADC.py
teensy_minimal_rpc/DMA.py
teensy_minimal_rpc/PIT.py
teensy_minimal_rpc/SIM.py
teensy_minimal_rpc/__init__.py
teensy_minimal_rpc/adc_sampler.py
teensy_minimal_rpc/config.py
teensy_minimal_rpc/node.py
teensy_minimal_rpc/proxy.py
teensy_minimal_rpc.egg-info/PKG-INFO
teensy_minimal_rpc.egg-info/SOURCES.txt
teensy_minimal_rpc.egg-info/dependency_links.txt
teensy_minimal_rpc.egg-info/pbr.json
teensy_minimal_rpc.egg-info/requires.txt
teensy_minimal_rpc.egg-info/top_level.txt
teensy_minimal_rpc/Arduino/library/TeensyMinimalRpc.zip
teensy_minimal_rpc/Arduino/library/TeensyMinimalRpc/library.properties
teensy_minimal_rpc/Arduino/library/TeensyMinimalRpc/src/TeensyMinimalRpc.h
teensy_minimal_rpc/Arduino/library/TeensyMinimalRpc/src/TeensyMinimalRpc/ADC.cpp
teensy_minimal_rpc/Arduino/library/TeensyMinimalRpc/src/TeensyMinimalRpc/ADC.h
teensy_minimal_rpc/Arduino/library/TeensyMinimalRpc/src/TeensyMinimalRpc/ADC_pb.c
teensy_minimal_rpc/Arduino/library/TeensyMinimalRpc/src/TeensyMinimalRpc/ADC_pb.h
teensy_minimal_rpc/Arduino/library/TeensyMinimalRpc/src/TeensyMinimalRpc/CommandProcessor.h
teensy_minimal_rpc/Arduino/library/TeensyMinimalRpc/src/TeensyMinimalRpc/Commands.h
teensy_minimal_rpc/Arduino/library/TeensyMinimalRpc/src/TeensyMinimalRpc/DMA.cpp
teensy_minimal_rpc/Arduino/library/TeensyMinimalRpc/src/TeensyMinimalRpc/DMA.h
teensy_minimal_rpc/Arduino/library/TeensyMinimalRpc/src/TeensyMinimalRpc/DMA_pb.c
teensy_minimal_rpc/Arduino/library/TeensyMinimalRpc/src/TeensyMinimalRpc/DMA_pb.h
teensy_minimal_rpc/Arduino/library/TeensyMinimalRpc/src/TeensyMinimalRpc/PIT.cpp
teensy_minimal_rpc/Arduino/library/TeensyMinimalRpc/src/TeensyMinimalRpc/PIT.h
teensy_minimal_rpc/Arduino/library/TeensyMinimalRpc/src/TeensyMinimalRpc/PIT_pb.c
teensy_minimal_rpc/Arduino/library/TeensyMinimalRpc/src/TeensyMinimalRpc/PIT_pb.h
teensy_minimal_rpc/Arduino/library/TeensyMinimalRpc/src/TeensyMinimalRpc/Properties.h
teensy_minimal_rpc/Arduino/library/TeensyMinimalRpc/src/TeensyMinimalRpc/RegisterMacros.h
teensy_minimal_rpc/Arduino/library/TeensyMinimalRpc/src/TeensyMinimalRpc/SIM.h
