Metadata-Version: 1.0
Name: teensy-minimal-rpc
Version: 0.2.post1
Summary: Template project demonstrating use of Arduino base node RPC framework.
Home-page: http://github.com/wheeler-microfluidics/teensy-minimal-rpc.git
Author: Christian Fobel
Author-email: christian@fobel.net
License: GPLv2
Platform: UNKNOWN
